<annotation>
	<folder>helmet</folder>
	<filename>41fd4ce3-2d4f-4948-8874-41ed3b925798___screen_shot_2017-07-03_at_12.11.48_pm.png</filename>
	<path>C:\helmet\41fd4ce3-2d4f-4948-8874-41ed3b925798___screen_shot_2017-07-03_at_12.11.48_pm.png</path>
	<source>
		<database>Unknown</database>
	</source>
	<size>
		<width>1000</width>
		<height>512</height>
		<depth>3</depth>
	</size>
	<segmented>0</segmented>
	<object>
		<name>with_helmet</name>
		<pose>Unspecified</pose>
		<truncated>0</truncated>
		<difficult>0</difficult>
		<bndbox>
			<xmin>510</xmin>
			<ymin>116</ymin>
			<xmax>657</xmax>
			<ymax>230</ymax>
		</bndbox>
	</object>
	<object>
		<name>with_helmet</name>
		<pose>Unspecified</pose>
		<truncated>0</truncated>
		<difficult>0</difficult>
		<bndbox>
			<xmin>337</xmin>
			<ymin>80</ymin>
			<xmax>448</xmax>
			<ymax>185</ymax>
		</bndbox>
	</object>
	<object>
		<name>with_helmet</name>
		<pose>Unspecified</pose>
		<truncated>0</truncated>
		<difficult>0</difficult>
		<bndbox>
			<xmin>796</xmin>
			<ymin>65</ymin>
			<xmax>895</xmax>
			<ymax>125</ymax>
		</bndbox>
	</object>
</annotation>
